mkdocs_py_ref_gen/__init__.py
mkdocs_py_ref_gen/cli.py
mkdocs_py_ref_gen/generator.py
mkdocs_py_ref_gen/plugin.py
mkdocs_py_ref_gen-0.1.1.dist-info/LICENSE
mkdocs_py_ref_gen-0.1.1.dist-info/METADATA
mkdocs_py_ref_gen-0.1.1.dist-info/WHEEL
mkdocs_py_ref_gen-0.1.1.dist-info/entry_points.txt
mkdocs_py_ref_gen-0.1.1.dist-info/RECORD
